ctek-0.3.0.dist-info/METADATA
ctek-0.3.0.dist-info/WHEEL
ctek-0.3.0.dist-info/licenses/LICENSE
ctek/__init__.py
ctek/nanogrid_air/nanogrid_air.py
ctek/nanogrid_air/types.py
ctek-0.3.0.dist-info/RECORD
