Metadata-Version: 2.1
Name: ctek
Version: 0.3.0
Summary: Python library to interact with multiple CTEK products through their open API:s
Author-Email: Carl Westman <carl.westman@ctek.com>
Project-URL: Repository, https://github.com/Wesztman/get-py-deps
Requires-Python: >=3.10
Requires-Dist: aiohttp~=3.9.5
Requires-Dist: ruff~=0.3.7; extra == "lint"
Requires-Dist: mypy~=1.9.0; extra == "lint"
Requires-Dist: pyright~=1.1.352; extra == "lint"
Requires-Dist: pytest~=8.1.1; extra == "test"
Requires-Dist: pytest-cov~=5.0.0; extra == "test"
Requires-Dist: coverage[toml]~=7.4.4; extra == "test"
Requires-Dist: pytest-mock~=3.14.0; extra == "test"
Requires-Dist: pytest-sugar~=1.0.0; extra == "test"
Requires-Dist: pytest-asyncio~=0.23.7; extra == "test"
Requires-Dist: pre-commit~=3.5.0; extra == "dev"
Requires-Dist: ctek[lint]; extra == "dev"
Requires-Dist: ctek[test]; extra == "dev"
Provides-Extra: lint
Provides-Extra: test
Provides-Extra: dev
